{
    "menus": [
        {
            "id": "menu1",
            "title": "Connect to Nature Menu",
            "image": "../assets/images/menus/nature.png",
            "description": [
                "Starter | Main course",
                "The best vegetal menu",
                "No gluten dishes included",
                "Available 24/7"
            ],
            "dishes": ["salad", "bruschetta", "garlic"],
            "price": 8.99
        },
        {
            "id": "menu2",
            "title": "Wombo Combo Menu",
            "image": "../assets/images/menus/menu2.png",
            "description": [
                "Main course | Drink",
                "All our classics available",
                "The choice of our clients",
                "Heavy full-stack meal"
            ],
            "dishes": ["calzone", "lasagna", "margherita"],
            "price": 15.99
        },
        {
            "id": "menu3",
            "title": "SegFault Rushed Menu",
            "image": "../assets/images/menus/menu3.png",
            "description": [
                "Main course | Drink",
                "The best foods available",
                "For a quick meal",
                "Affordable and Fast"
            ],
            "dishes": ["penne", "ravioli", "carbonara", "spaghetti", "espresso"],
            "price": 19.99
        },
        {
            "id": "menu4",
            "title": "Sweet BlueStacks",
            "image": "../assets/images/menus/menu3.png",
            "description": [],
            "price": 4.99
        },
        {
            "id": "menu5",
            "title": "Java & Tea Runtime",
            "image": "../assets/images/menus/menu3.png",
            "description": [],
            "price": 4.99
        },
        {
            "id": "menu6",
            "title": "Git Merge Menu",
            "image": "../assets/images/menus/git.png",
            "description": [
                "Starter | Main course | Dessert",
                "Most foods available",
                "Perfectly combined",
                "Affordable and delicious"
            ],
            "price": 12.99
        },
        {
            "id": "menu7",
            "title": "Import * Menu",
            "image": "../assets/images/menus/import.png",
            "description": [
                "Starter | Main course | Drink | Dessert",
                "Every dish available",
                "Our most complete menu",
                "The best experience"
            ],
            "price": 24.99
        },
        {
            "id": "menu8",
            "title": "Aymane Menu",
            "image": "../assets/images/menus/menu3.png",
            "description": [
                "Meal",
                "The best meal of the restaurant",
                "It's fast, very fast.",
                "Not cheap, but high quality"
            ],
            "price": 3979.99
        }
    ]
}
